openwind/__init__.py
openwind/algo_optimization.py
openwind/compute_transfer_matrix.py
openwind/impedance_computation.py
openwind/impedance_tools.py
openwind/macro_OW2Freecad.py
openwind/parsing_tools.py
openwind/simu_anim.py
openwind/temporal_simulation.py
openwind/tracker.py
openwind/continuous/__init__.py
openwind/continuous/excitator.py
openwind/continuous/instrument_physics.py
openwind/continuous/junction.py
openwind/continuous/netlist.py
openwind/continuous/parametrique_optim.py
openwind/continuous/physical_radiation.py
openwind/continuous/physics.py
openwind/continuous/pipe.py
openwind/continuous/radiation_from_data.py
openwind/continuous/radiation_model.py
openwind/continuous/radiation_pulsating_sphere.py
openwind/continuous/radiation_silva.py
openwind/continuous/scaling.py
openwind/continuous/thermoviscous_models.py
openwind/continuous/tonehole.py
openwind/design/__init__.py
openwind/design/bessel.py
openwind/design/circle.py
openwind/design/cone.py
openwind/design/design_parameter.py
openwind/design/design_shape.py
openwind/design/exponential.py
openwind/design/shape_slice.py
openwind/design/spline.py
openwind/discretization/__init__.py
openwind/discretization/discretized_pipe.py
openwind/discretization/element.py
openwind/discretization/glQuad.py
openwind/discretization/mesh.py
openwind/frequential/__init__.py
openwind/frequential/frequential_component.py
openwind/frequential/frequential_interpolation.py
openwind/frequential/frequential_junction_discontinuity.py
openwind/frequential/frequential_junction_simple.py
openwind/frequential/frequential_junction_switch.py
openwind/frequential/frequential_junction_tjoint.py
openwind/frequential/frequential_pipe_diffusive_representation.py
openwind/frequential/frequential_pipe_fem.py
openwind/frequential/frequential_pipe_tmm.py
openwind/frequential/frequential_pressure_condition.py
openwind/frequential/frequential_radiation.py
openwind/frequential/frequential_radiation1dof.py
openwind-0.12.3.dist-info/LICENSE
openwind-0.12.3.dist-info/METADATA
openwind-0.12.3.dist-info/WHEEL
openwind-0.12.3.dist-info/entry_points.txt
openwind-0.12.3.dist-info/top_level.txt
openwind-0.12.3.dist-info/RECORD
