Metadata-Version: 2.1
Name: openwind
Version: 0.12.3
Summary: Open source library to design wind instruments
Home-page: https://files.inria.fr/openwind/docs
Author: Inria
Author-email: openwind-contact@inria.fr
License: GPLv3
Platform: UNKNOWN
Classifier: License :: OSI Approved :: GNU General Public License v3 (GPLv3)
Classifier: Programming Language :: Python :: 3
License-File: LICENSE
Requires-Dist: h5py
Requires-Dist: matplotlib
Requires-Dist: numpy
Requires-Dist: scipy
